src/__init__.py
src/logic.py
src/main.py
testprojvismaya-0.0.4.dist-info/METADATA
testprojvismaya-0.0.4.dist-info/WHEEL
testprojvismaya-0.0.4.dist-info/entry_points.txt
testprojvismaya-0.0.4.dist-info/top_level.txt
testprojvismaya-0.0.4.dist-info/RECORD
