Metadata-Version: 2.1
Name: testprojvismaya
Version: 0.0.4
Summary: An application that informs you of the time in different locations and timezones
Home-page: https://github.com/VismayaM-2003/sample.git
Author: vismaya
Author-email: muruganvichunni@gmail.com
Classifier: Programming Language :: Python :: 3
Classifier: License :: OSI Approved :: MIT License
Classifier: Operating System :: OS Independent
Requires-Dist: click
Requires-Dist: pytz
